README.md
setup.py
bencode/__init__.py
bencode/decoder.py
bencode/define.py
bencode/encoder.py
torrent_bencode3.egg-info/PKG-INFO
torrent_bencode3.egg-info/SOURCES.txt
torrent_bencode3.egg-info/dependency_links.txt
torrent_bencode3.egg-info/top_level.txt