Metadata-Version: 2.1
Name: torrent-bencode3
Version: 0.1.1
Summary: torrent文件的编码、解码
Home-page: http://github.com/skytoup/torrent-bencode3
Author: skytoup
Author-email: skytoupone1@gmail.com
License: MIT
Keywords: torrent,bencode,encode,decode
Platform: any
Requires-Python: >=3.5
